Metadata-Version: 2.1
Name: odoo-addon-account_banking_pain_base
Version: 18.0.1.1.0.3
Requires-Python: >=3.10
Requires-Dist: lxml
Requires-Dist: odoo-addon-account_payment_order==18.0.*
Requires-Dist: odoo==18.0.*
Requires-Dist: unidecode
Summary: Base module for PAIN file generation
Home-page: https://github.com/OCA/bank-payment
License: AGPL-3
Author: Akretion, Noviat, Tecnativa, Odoo Community Association (OCA)
Author-email: support@odoo-community.org
Classifier: Programming Language :: Python
Classifier: Framework :: Odoo
Classifier: Framework :: Odoo :: 18.0
Classifier: License :: OSI Approved :: GNU Affero General Public License v3
